pyoocass/Database.py
pyoocass/Keyspace.py
pyoocass/Table.py
pyoocass/__init__.py
pyoocass-0.0.5.dist-info/LICENSE
pyoocass-0.0.5.dist-info/METADATA
pyoocass-0.0.5.dist-info/WHEEL
pyoocass-0.0.5.dist-info/top_level.txt
pyoocass-0.0.5.dist-info/RECORD
