Metadata-Version: 2.1
Name: pyoocass
Version: 0.0.5
Summary: Python Object-Orinted Cassandra interface
Home-page: https://github.com/Silvarion/pyoocass
Author: Jesus Alejandro Sanchez Davila
Author-email: jsanchez.consultant@gmail.com
License: UNKNOWN
Platform: UNKNOWN
Classifier: Programming Language :: Python :: 3
Classifier: License :: OSI Approved :: MIT License
Classifier: Operating System :: OS Independent
Requires-Python: >=3.6
License-File: LICENSE
Requires-Dist: cassandra-driver
Requires-Dist: cassandra-sigv4
Requires-Dist: time-uuid
